dicomanonymizer/__init__.py
dicomanonymizer/anonymizer.py
dicomanonymizer/dicomfields_selector.py
dicomanonymizer/format_tag.py
dicomanonymizer/simpledicomanonymizer.py
dicomanonymizer/dicom_anonymization_databases/__init__.py
dicomanonymizer/dicom_anonymization_databases/dicomfields_2023.py
dicomanonymizer/dicom_anonymization_databases/dicomfields_2024b.py
dicom_anonymizer-1.0.13.post1.dist-info/LICENSE
dicom_anonymizer-1.0.13.post1.dist-info/METADATA
dicom_anonymizer-1.0.13.post1.dist-info/WHEEL
dicom_anonymizer-1.0.13.post1.dist-info/entry_points.txt
dicom_anonymizer-1.0.13.post1.dist-info/top_level.txt
dicom_anonymizer-1.0.13.post1.dist-info/RECORD
