Metadata-Version: 2.1
Name: dicom_anonymizer
Version: 1.0.13.post1
Summary: Program to anonymize dicom files with default and custom rules
Home-page: https://github.com/KitwareMedical/dicom-anonymizer
Author: Laurenn Lam
Author-email: laurenn.lam@kitware.com
Project-URL: Bug Tracker, https://github.com/KitwareMedical/dicom-anonymizer/issues
Keywords: dicom,anonymizer,medical
Classifier: Development Status :: 3 - Alpha
Classifier: Intended Audience :: Science/Research
Classifier: Topic :: Software Development :: Build Tools
Classifier: License :: OSI Approved :: BSD License
Classifier: Natural Language :: English
Classifier: Programming Language :: Python
Requires-Python: >=3.6
License-File: LICENSE
Requires-Dist: pydicom <3
Requires-Dist: tqdm
Provides-Extra: dev
Requires-Dist: pytest ; extra == 'dev'
Requires-Dist: bs4 ; extra == 'dev'
Requires-Dist: fire ; extra == 'dev'
Requires-Dist: requests ; extra == 'dev'
Requires-Dist: pre-commit ; extra == 'dev'
Requires-Dist: ruff ; extra == 'dev'
